tkns/__init__.py
tkns-0.1.dist-info/DESCRIPTION.rst
tkns-0.1.dist-info/METADATA
tkns-0.1.dist-info/RECORD
tkns-0.1.dist-info/WHEEL
tkns-0.1.dist-info/metadata.json
tkns-0.1.dist-info/top_level.txt
